SeedWaterSegmenter
