Metadata-Version: 2.1
Name: SeedWaterSegmenter
Version: 0.7.1
Summary: graphical program to interactively segment image stacks of cells in tissue with edge-labels (aka. white outlines)
Home-page: http://pypi.python.org/pypi/SeedWaterSegmenter/
Author: David N. Mashburn
Author-email: david.n.mashburn@gmail.com
License: LICENSE.txt
Platform: UNKNOWN
License-File: LICENSE.txt
